earl.pyd
earl_etf-2.1.2.dist-info/DESCRIPTION.rst
earl_etf-2.1.2.dist-info/METADATA
earl_etf-2.1.2.dist-info/RECORD
earl_etf-2.1.2.dist-info/WHEEL
earl_etf-2.1.2.dist-info/metadata.json
earl_etf-2.1.2.dist-info/top_level.txt
