Metadata-Version: 1.0
Name: earl-etf
Version: 2.1.2
Summary: Earl-etf, the fanciest External Term Format packer and unpacker available for Python.
Home-page: https://github.com/ccubed/Earl
Author: Charles Click
Author-email: CharlesClick@vertinext.com
License: MIT
Keywords: Erlang ETF External Term Format
Platform: UNKNOWN
